opensesame_plugins/radboudbox/__init__.py
opensesame_plugins/radboudbox/radboudbox_get_buttons_start/__init__.py
opensesame_plugins/radboudbox/radboudbox_get_buttons_start/radboudbox_get_buttons_start.png
opensesame_plugins/radboudbox/radboudbox_get_buttons_start/radboudbox_get_buttons_start.py
opensesame_plugins/radboudbox/radboudbox_get_buttons_start/radboudbox_get_buttons_start_large.png
opensesame_plugins/radboudbox/radboudbox_get_buttons_wait/__init__.py
opensesame_plugins/radboudbox/radboudbox_get_buttons_wait/radboudbox_get_buttons_wait.png
opensesame_plugins/radboudbox/radboudbox_get_buttons_wait/radboudbox_get_buttons_wait.py
opensesame_plugins/radboudbox/radboudbox_get_buttons_wait/radboudbox_get_buttons_wait_large.png
opensesame_plugins/radboudbox/radboudbox_init/__init__.py
opensesame_plugins/radboudbox/radboudbox_init/radboudbox_init.png
opensesame_plugins/radboudbox/radboudbox_init/radboudbox_init.py
opensesame_plugins/radboudbox/radboudbox_init/radboudbox_init_large.png
opensesame_plugins/radboudbox/radboudbox_send_control/__init__.py
opensesame_plugins/radboudbox/radboudbox_send_control/radboudbox_send_control.png
opensesame_plugins/radboudbox/radboudbox_send_control/radboudbox_send_control.py
opensesame_plugins/radboudbox/radboudbox_send_control/radboudbox_send_control_large.png
opensesame_plugins/radboudbox/radboudbox_send_trigger/__init__.py
opensesame_plugins/radboudbox/radboudbox_send_trigger/radboudbox_send_trigger.png
opensesame_plugins/radboudbox/radboudbox_send_trigger/radboudbox_send_trigger.py
opensesame_plugins/radboudbox/radboudbox_send_trigger/radboudbox_send_trigger_large.png
opensesame_plugins/radboudbox/radboudbox_wait_buttons/__init__.py
opensesame_plugins/radboudbox/radboudbox_wait_buttons/radboudbox_wait_buttons.png
opensesame_plugins/radboudbox/radboudbox_wait_buttons/radboudbox_wait_buttons.py
opensesame_plugins/radboudbox/radboudbox_wait_buttons/radboudbox_wait_buttons_large.png
opensesame_plugin_radboudbox-4.6.0.dist-info/COPYING
opensesame_plugin_radboudbox-4.6.0.dist-info/LICENSE.md
opensesame_plugin_radboudbox-4.6.0.dist-info/METADATA
opensesame_plugin_radboudbox-4.6.0.dist-info/WHEEL
opensesame_plugin_radboudbox-4.6.0.dist-info/RECORD
