Metadata-Version: 2.3
Name: opensesame-plugin-radboudbox
Version: 4.6.0
Summary: An OpenSesame Plug-in for collecting button responses, audio detection, voice key and sending stimulus synchronization triggers with the Radboud Buttonbox to data acquisition systems
License: LICENSE.md
Author: Bob Rosbag
Author-email: debian@bobrosbag.nl
Requires-Python: >=3.7
Classifier: License :: Other/Proprietary License
Classifier: Programming Language :: Python :: 3
Classifier: Programming Language :: Python :: 3.7
Classifier: Programming Language :: Python :: 3.8
Classifier: Programming Language :: Python :: 3.9
Classifier: Programming Language :: Python :: 3.10
Classifier: Programming Language :: Python :: 3.11
Classifier: Programming Language :: Python :: 3.12
Classifier: Programming Language :: Python :: 3.13
Requires-Dist: rusocsci
Project-URL: Homepage, https://github.com/dev-jam/opensesame-plugin-radboudbox
Project-URL: Repository, https://github.com/dev-jam/opensesame-plugin-radboudbox
